windc_data/__init__.py
windc_data/gams_windc.py
windc_data/gmsxfr.py
windc_data/loader.py
windc_data/mappings.py
windc_data/windc_2_0_1/__init__.py
windc_data/windc_2_0_1/gdx_data.py
windc_data/windc_2_0_1/join.py
windc_data/windc_2_0_1/xfrm.py
windc_data/windc_2_0_1/parse/__init__.py
windc_data/windc_2_0_1/parse/bea_gsp.py
windc_data/windc_2_0_1/parse/bea_pce.py
windc_data/windc_2_0_1/parse/bea_supply.py
windc_data/windc_2_0_1/parse/bea_supply_det.py
windc_data/windc_2_0_1/parse/bea_use.py
windc_data/windc_2_0_1/parse/bea_use_det.py
windc_data/windc_2_0_1/parse/census_sgf.py
windc_data/windc_2_0_1/parse/cfs.py
windc_data/windc_2_0_1/parse/eia.py
windc_data/windc_2_0_1/parse/nass.py
windc_data/windc_2_0_1/parse/sgf_table_sums.py
windc_data/windc_2_0_1/parse/state_exim.py
windc_data/windc_2_1/__init__.py
windc_data/windc_2_1/gdx_data.py
windc_data/windc_2_1/join.py
windc_data/windc_2_1/xfrm.py
windc_data/windc_2_1/parse/__init__.py
windc_data/windc_2_1/parse/bea_gsp.py
windc_data/windc_2_1/parse/bea_pce.py
windc_data/windc_2_1/parse/bea_supply.py
windc_data/windc_2_1/parse/bea_supply_det.py
windc_data/windc_2_1/parse/bea_use.py
windc_data/windc_2_1/parse/bea_use_det.py
windc_data/windc_2_1/parse/census_sgf.py
windc_data/windc_2_1/parse/cfs.py
windc_data/windc_2_1/parse/eia.py
windc_data/windc_2_1/parse/nass.py
windc_data/windc_2_1/parse/sgf_table_sums.py
windc_data/windc_2_1/parse/state_exim.py
windc_data-0.1.13.dist-info/LICENSE
windc_data-0.1.13.dist-info/METADATA
windc_data-0.1.13.dist-info/WHEEL
windc_data-0.1.13.dist-info/top_level.txt
windc_data-0.1.13.dist-info/RECORD
