Metadata-Version: 2.1
Name: windc-data
Version: 0.1.13
Summary: A helper package to read/write WiNDC Data
Home-page: https://windc.wisc.edu
Author: Adam Christensen
Author-email: achristensen@gams.com
License: UNKNOWN
Platform: UNKNOWN
Classifier: Programming Language :: Python :: 3
Classifier: License :: OSI Approved :: MIT License
Classifier: Operating System :: OS Independent
Requires-Python: >=3.6
Requires-Dist: gams
Requires-Dist: ipython
Requires-Dist: networkx
Requires-Dist: pandas
Requires-Dist: pip
Requires-Dist: tqdm
Requires-Dist: xlrd
Requires-Dist: argparse
Requires-Dist: schema
Requires-Dist: terminaltables
